zmapg/__init__.py
zmapg/__main__.py
zmapg/app.py
zmapg-1.0.0.dist-info/METADATA
zmapg-1.0.0.dist-info/WHEEL
zmapg-1.0.0.dist-info/entry_points.txt
zmapg-1.0.0.dist-info/top_level.txt
zmapg-1.0.0.dist-info/RECORD
