Metadata-Version: 2.1
Name: zmapg
Version: 1.0.0
Summary: ZMap GUI application for zmap-cli tool
Home-page: https://github.com/atiilla/zmapg
Author: atiilla
License: MIT
Keywords: zmap ui tkinter
Requires-Dist: tk
Requires-Dist: ttkthemes
